{"_type":"export","__export_format":4,"__export_date":"2021-11-23T07:07:28.950Z","__export_source":"insomnia.desktop.app:v2021.6.0","resources":[{"_id":"req_ad312dce499047c1b3bc6f0c82038726","parentId":"wrk_2df22d9915c4490eb040c83342d1f745","modified":1637651048246,"created":1637540642380,"url":"{{host}}/.netlify/functions/graphql","name":"Get Current User","description":"","method":"POST","body":{"mimeType":"application/graphql","text":"{\"query\":\"query __REDWOOD__AUTH_GET_CURRENT_USER { \\n  redwood { \\n    currentUser \\n  } \\n}\",\"operationName\":\"__REDWOOD__AUTH_GET_CURRENT_USER\"}"},"parameters":[],"headers":[{"name":"Connection","value":"keep-alive","id":"pair_46b9b06c34d348a592b74406d63f303c","disabled":false},{"name":"authorization","value":"{{myBearer}}","id":"pair_dd4d347b547f4ecdaa1cec7895338184","disabled":false},{"name":"content-type","value":"application/json","id":"pair_eeecb84539f34cacae18836e5395a4d1"},{"name":"auth-provider","value":"dbAuth","id":"pair_096fdb3dd37249ad87a28d0f28747f63","disabled":false},{"name":"Cookie","value":"session={{mySession}}","id":"pair_a93999a7a32a465e9819095263a5c343","disabled":false}],"authentication":{},"metaSortKey":-1637624833781,"isPrivate":false,"settingStoreCookies":true,"settingSendCookies":true,"settingDisableRenderRequestBody":false,"settingEncodeUrl":true,"settingRebuildPath":true,"settingFollowRedirects":"global","_type":"request"},{"_id":"wrk_2df22d9915c4490eb040c83342d1f745","parentId":null,"modified":1637540192209,"created":1637540192209,"name":"Tskr","description":"","scope":"collection","_type":"workspace"},{"_id":"req_8a984d74cb2d4ca288ec7e317aedb1b2","parentId":"wrk_2df22d9915c4490eb040c83342d1f745","modified":1637651046695,"created":1637644300360,"url":"{{host}}/.netlify/functions/graphql","name":"Introspection Query","description":"","method":"POST","body":{"mimeType":"application/graphql","text":"{\"query\":\"\\n    query IntrospectionQuery {\\n      __schema {\\n        \\n        queryType { name }\\n        mutationType { name }\\n        subscriptionType { name }\\n        types {\\n          ...FullType\\n        }\\n        directives {\\n          name\\n          description\\n          \\n          locations\\n          args {\\n            ...InputValue\\n          }\\n        }\\n      }\\n    }\\n\\n    fragment FullType on __Type {\\n      kind\\n      name\\n      description\\n      fields(includeDeprecated: true) {\\n        name\\n        description\\n        args {\\n          ...InputValue\\n        }\\n        type {\\n          ...TypeRef\\n        }\\n        isDeprecated\\n        deprecationReason\\n      }\\n      inputFields {\\n        ...InputValue\\n      }\\n      interfaces {\\n        ...TypeRef\\n      }\\n      enumValues(includeDeprecated: true) {\\n        name\\n        description\\n        isDeprecated\\n        deprecationReason\\n      }\\n      possibleTypes {\\n        ...TypeRef\\n      }\\n    }\\n\\n    fragment InputValue on __InputValue {\\n      name\\n      description\\n      type { ...TypeRef }\\n      defaultValue\\n    }\\n\\n    fragment TypeRef on __Type {\\n      kind\\n      name\\n      ofType {\\n        kind\\n        name\\n        ofType {\\n          kind\\n          name\\n          ofType {\\n            kind\\n            name\\n            ofType {\\n              kind\\n              name\\n              ofType {\\n                kind\\n                name\\n                ofType {\\n                  kind\\n                  name\\n                  ofType {\\n                    kind\\n                    name\\n                  }\\n                }\\n              }\\n            }\\n          }\\n        }\\n      }\\n    }\\n  \"}"},"parameters":[],"headers":[{"name":"Connection","value":"keep-alive","id":"pair_46b9b06c34d348a592b74406d63f303c","disabled":false},{"name":"authorization","value":"{{myBearer}}","id":"pair_dd4d347b547f4ecdaa1cec7895338184","disabled":false},{"name":"content-type","value":"application/json","id":"pair_eeecb84539f34cacae18836e5395a4d1"},{"name":"auth-provider","value":"dbAuth","id":"pair_096fdb3dd37249ad87a28d0f28747f63","disabled":false},{"name":"Cookie","value":"session={{mySession}}","id":"pair_a93999a7a32a465e9819095263a5c343","disabled":false}],"authentication":{},"metaSortKey":-1637624833756,"isPrivate":false,"settingStoreCookies":true,"settingSendCookies":true,"settingDisableRenderRequestBody":false,"settingEncodeUrl":true,"settingRebuildPath":true,"settingFollowRedirects":"global","_type":"request"},{"_id":"req_2de089fc2fb24ae58f0cafdfb20108dd","parentId":"fld_068c2d5740e24c498fb50bdc89060503","modified":1637651003708,"created":1637543285441,"url":"{{host}}/.netlify/functions/graphql","name":"Groups","description":"","method":"POST","body":{"mimeType":"application/graphql","text":"{\"query\":\" query getGroups {\\n  groups {\\n    id\\n    name\\n    createdAt\\n  }\\n}\",\"operationName\":\"getGroups\"}"},"parameters":[],"headers":[{"name":"Connection","value":"keep-alive","id":"pair_46b9b06c34d348a592b74406d63f303c","disabled":false},{"name":"authorization","value":"{{myBearer}}","id":"pair_dd4d347b547f4ecdaa1cec7895338184","disabled":false},{"name":"content-type","value":"application/json","id":"pair_eeecb84539f34cacae18836e5395a4d1"},{"name":"auth-provider","value":"dbAuth","id":"pair_096fdb3dd37249ad87a28d0f28747f63","disabled":false},{"name":"Cookie","value":"session={{mySession}}","id":"pair_a93999a7a32a465e9819095263a5c343","disabled":false}],"authentication":{},"metaSortKey":-1636987936082.5,"isPrivate":false,"settingStoreCookies":true,"settingSendCookies":true,"settingDisableRenderRequestBody":false,"settingEncodeUrl":true,"settingRebuildPath":true,"settingFollowRedirects":"global","_type":"request"},{"_id":"fld_068c2d5740e24c498fb50bdc89060503","parentId":"wrk_2df22d9915c4490eb040c83342d1f745","modified":1637543275881,"created":1637543275881,"name":"Groups","description":"","environment":{},"environmentPropertyOrder":null,"metaSortKey":-1637543275881,"_type":"request_group"},{"_id":"req_8aa1b6702e434e958c97aa9390fa05dc","parentId":"fld_068c2d5740e24c498fb50bdc89060503","modified":1637651050244,"created":1637625245706,"url":"{{host}}/.netlify/functions/graphql","name":"Create Group","description":"","method":"POST","body":{"mimeType":"application/graphql","text":"{\"query\":\"  mutation CreateGroupMutation(\\n    $input: CreateGroupInput!\\n  ) {\\n    createGroup(input: $input) {\\n      id\\n      name\\n      description\\n    }\\n  }\",\"variables\":{\"input\":{\"name\":\"Workers\",\"description\":\"Workers is plural\"}},\"operationName\":\"CreateGroupMutation\"}"},"parameters":[],"headers":[{"name":"Connection","value":"keep-alive","id":"pair_46b9b06c34d348a592b74406d63f303c","disabled":false},{"name":"authorization","value":"{{myBearer}}","id":"pair_dd4d347b547f4ecdaa1cec7895338184","disabled":false},{"name":"content-type","value":"application/json","id":"pair_eeecb84539f34cacae18836e5395a4d1"},{"name":"auth-provider","value":"dbAuth","id":"pair_096fdb3dd37249ad87a28d0f28747f63","disabled":false},{"name":"Cookie","value":"session={{mySession}}","id":"pair_a93999a7a32a465e9819095263a5c343","disabled":false}],"authentication":{},"metaSortKey":-1636987936132.5,"isPrivate":false,"settingStoreCookies":true,"settingSendCookies":true,"settingDisableRenderRequestBody":false,"settingEncodeUrl":true,"settingRebuildPath":true,"settingFollowRedirects":"global","_type":"request"},{"_id":"req_5f49303f4e89481aae1e2bc856e181d9","parentId":"fld_068c2d5740e24c498fb50bdc89060503","modified":1637651051257,"created":1637625284555,"url":"{{host}}/.netlify/functions/graphql","name":"Group by id","description":"","method":"POST","body":{"mimeType":"application/graphql","text":"{\"query\":\"query getGroup($id: Int!) {\\n  group: group(id: $id) {\\n    id\\n    name\\n    createdAt\\n    updatedAt\\n  }\\n}\",\"variables\":{\"id\":73},\"operationName\":\"getGroup\"}"},"parameters":[],"headers":[{"name":"Connection","value":"keep-alive","id":"pair_46b9b06c34d348a592b74406d63f303c","disabled":false},{"name":"authorization","value":"{{myBearer}}","id":"pair_dd4d347b547f4ecdaa1cec7895338184","disabled":false},{"name":"content-type","value":"application/json","id":"pair_eeecb84539f34cacae18836e5395a4d1"},{"name":"auth-provider","value":"dbAuth","id":"pair_096fdb3dd37249ad87a28d0f28747f63","disabled":false},{"name":"Cookie","value":"session={{mySession}}","id":"pair_a93999a7a32a465e9819095263a5c343","disabled":false}],"authentication":{},"metaSortKey":-1636987936032.5,"isPrivate":false,"settingStoreCookies":true,"settingSendCookies":true,"settingDisableRenderRequestBody":false,"settingEncodeUrl":true,"settingRebuildPath":true,"settingFollowRedirects":"global","_type":"request"},{"_id":"req_587ccfb87b8d47b281f305d989201d23","parentId":"fld_068c2d5740e24c498fb50bdc89060503","modified":1637651052074,"created":1637625637461,"url":"{{host}}/.netlify/functions/graphql","name":"Update Group","description":"","method":"POST","body":{"mimeType":"application/graphql","text":"{\"query\":\"  mutation UpdateGroupMutation(\\n    $id: Int!\\n    $input: UpdateGroupInput!\\n  ) {\\n    updateGroup(id: $id, input: $input) {\\n      id\\n      name\\n    }\\n  }\",\"variables\":{\"id\":73,\"input\":{\"name\":\"Worker Bees\"}},\"operationName\":\"UpdateGroupMutation\"}"},"parameters":[],"headers":[{"name":"Connection","value":"keep-alive","id":"pair_46b9b06c34d348a592b74406d63f303c","disabled":false},{"name":"authorization","value":"{{myBearer}}","id":"pair_dd4d347b547f4ecdaa1cec7895338184","disabled":false},{"name":"content-type","value":"application/json","id":"pair_eeecb84539f34cacae18836e5395a4d1"},{"name":"auth-provider","value":"dbAuth","id":"pair_096fdb3dd37249ad87a28d0f28747f63","disabled":false},{"name":"Cookie","value":"session={{mySession}}","id":"pair_a93999a7a32a465e9819095263a5c343","disabled":false}],"authentication":{},"metaSortKey":-1636987935982.5,"isPrivate":false,"settingStoreCookies":true,"settingSendCookies":true,"settingDisableRenderRequestBody":false,"settingEncodeUrl":true,"settingRebuildPath":true,"settingFollowRedirects":"global","_type":"request"},{"_id":"req_329efeac6cd147fab423ce31a27a0fb7","parentId":"fld_068c2d5740e24c498fb50bdc89060503","modified":1637651053197,"created":1637625766604,"url":"{{host}}/.netlify/functions/graphql","name":"Delete Group","description":"","method":"POST","body":{"mimeType":"application/graphql","text":"{\"query\":\"  mutation DeleteUserMutation($id: Int!) {\\n    deleteGroup(id: $id) {\\n      id\\n      name\\n    }\\n  }\",\"variables\":{\"id\":73},\"operationName\":\"DeleteUserMutation\"}"},"parameters":[],"headers":[{"name":"Connection","value":"keep-alive","id":"pair_46b9b06c34d348a592b74406d63f303c","disabled":false},{"name":"authorization","value":"{{myBearer}}","id":"pair_dd4d347b547f4ecdaa1cec7895338184","disabled":false},{"name":"content-type","value":"application/json","id":"pair_eeecb84539f34cacae18836e5395a4d1"},{"name":"auth-provider","value":"dbAuth","id":"pair_096fdb3dd37249ad87a28d0f28747f63","disabled":false},{"name":"Cookie","value":"session={{mySession}}","id":"pair_a93999a7a32a465e9819095263a5c343","disabled":false}],"authentication":{},"metaSortKey":-1636932707191.25,"isPrivate":false,"settingStoreCookies":true,"settingSendCookies":true,"settingDisableRenderRequestBody":false,"settingEncodeUrl":true,"settingRebuildPath":true,"settingFollowRedirects":"global","_type":"request"},{"_id":"req_9ad71b6ccd1c41ddaa33b49bd0353bbe","parentId":"fld_5af52d0a246640b29db28d4926aa6a99","modified":1637651025139,"created":1637618263419,"url":"{{host}}/.netlify/functions/graphql","name":"Create User","description":"","method":"POST","body":{"mimeType":"application/graphql","text":"{\"query\":\"  mutation CreateUserMutation(\\n    $input: CreateUserInput!\\n  ) {\\n    createUser(input: $input) {\\n      id\\n      name\\n      email\\n    }\\n  }\",\"variables\":{\"input\":{\"name\":\"Jace-from-insomnia\",\"email\":\"afd\",\"hashedPassword\":\"test\"}},\"operationName\":\"CreateUserMutation\"}"},"parameters":[],"headers":[{"name":"Connection","value":"keep-alive","id":"pair_46b9b06c34d348a592b74406d63f303c","disabled":false},{"name":"authorization","value":"{{myBearer}}","id":"pair_dd4d347b547f4ecdaa1cec7895338184","disabled":false},{"name":"content-type","value":"application/json","id":"pair_eeecb84539f34cacae18836e5395a4d1"},{"name":"auth-provider","value":"dbAuth","id":"pair_096fdb3dd37249ad87a28d0f28747f63","disabled":false},{"name":"Cookie","value":"session={{mySession}}","id":"pair_a93999a7a32a465e9819095263a5c343","disabled":false}],"authentication":{},"metaSortKey":-1636767020717.5,"isPrivate":false,"settingStoreCookies":true,"settingSendCookies":true,"settingDisableRenderRequestBody":false,"settingEncodeUrl":true,"settingRebuildPath":true,"settingFollowRedirects":"global","_type":"request"},{"_id":"fld_5af52d0a246640b29db28d4926aa6a99","parentId":"wrk_2df22d9915c4490eb040c83342d1f745","modified":1637624833731,"created":1637624833731,"name":"Users","description":"","environment":{},"environmentPropertyOrder":null,"metaSortKey":-1637624833731,"_type":"request_group"},{"_id":"req_db926eb113fe46a5b0cf0de7f4aa41a7","parentId":"fld_5af52d0a246640b29db28d4926aa6a99","modified":1637651030549,"created":1637624968787,"url":"{{host}}/.netlify/functions/graphql","name":"Users","description":"","method":"POST","body":{"mimeType":"application/graphql","text":"{\"query\":\" query getUsers {\\n  users {\\n    id\\n    name\\n    createdAt\\n    updatedAt\\n    email\\n  }\\n}\",\"operationName\":\"getUsers\"}"},"parameters":[],"headers":[{"name":"Connection","value":"keep-alive","id":"pair_46b9b06c34d348a592b74406d63f303c","disabled":false},{"name":"authorization","value":"{{myBearer}}","id":"pair_dd4d347b547f4ecdaa1cec7895338184","disabled":false},{"name":"content-type","value":"application/json","id":"pair_eeecb84539f34cacae18836e5395a4d1"},{"name":"auth-provider","value":"dbAuth","id":"pair_096fdb3dd37249ad87a28d0f28747f63","disabled":false},{"name":"Cookie","value":"session={{mySession}}","id":"pair_a93999a7a32a465e9819095263a5c343","disabled":false}],"authentication":{},"metaSortKey":-1636711791876.25,"isPrivate":false,"settingStoreCookies":true,"settingSendCookies":true,"settingDisableRenderRequestBody":false,"settingEncodeUrl":true,"settingRebuildPath":true,"settingFollowRedirects":"global","_type":"request"},{"_id":"req_bc0bc56a63bd49b2ab94518321501c41","parentId":"fld_5af52d0a246640b29db28d4926aa6a99","modified":1637651035365,"created":1637625139745,"url":"{{host}}/.netlify/functions/graphql","name":"User by id","description":"","method":"POST","body":{"mimeType":"application/graphql","text":"{\"query\":\"query getUser($id: Int!) {\\n  user: user(id: $id) {\\n    id\\n    name\\n    createdAt\\n    updatedAt\\n    email\\n  }\\n}\",\"variables\":{\"id\":1363},\"operationName\":\"getUser\"}"},"parameters":[],"headers":[{"name":"Connection","value":"keep-alive","id":"pair_46b9b06c34d348a592b74406d63f303c","disabled":false},{"name":"authorization","value":"{{myBearer}}","id":"pair_dd4d347b547f4ecdaa1cec7895338184","disabled":false},{"name":"content-type","value":"application/json","id":"pair_eeecb84539f34cacae18836e5395a4d1"},{"name":"auth-provider","value":"dbAuth","id":"pair_096fdb3dd37249ad87a28d0f28747f63","disabled":false},{"name":"Cookie","value":"session={{mySession}}","id":"pair_a93999a7a32a465e9819095263a5c343","disabled":false}],"authentication":{},"metaSortKey":-1636684177455.625,"isPrivate":false,"settingStoreCookies":true,"settingSendCookies":true,"settingDisableRenderRequestBody":false,"settingEncodeUrl":true,"settingRebuildPath":true,"settingFollowRedirects":"global","_type":"request"},{"_id":"req_fe7b519b809f4bf1964e5d02a1b4ec52","parentId":"fld_5af52d0a246640b29db28d4926aa6a99","modified":1637651039718,"created":1637625349867,"url":"{{host}}/.netlify/functions/graphql","name":"Update User","description":"","method":"POST","body":{"mimeType":"application/graphql","text":"{\"query\":\"  mutation UpdateUserMutation(\\n    $id: Int!\\n    $input: UpdateUserInput!\\n  ) {\\n    updateUser(id: $id, input: $input) {\\n      id\\n      name\\n    }\\n  }\",\"variables\":{\"id\":1363,\"input\":{\"name\":\"SrRobot\"}},\"operationName\":\"UpdateUserMutation\"}"},"parameters":[],"headers":[{"name":"Connection","value":"keep-alive","id":"pair_46b9b06c34d348a592b74406d63f303c","disabled":false},{"name":"authorization","value":"{{myBearer}}","id":"pair_dd4d347b547f4ecdaa1cec7895338184","disabled":false},{"name":"content-type","value":"application/json","id":"pair_eeecb84539f34cacae18836e5395a4d1"},{"name":"auth-provider","value":"dbAuth","id":"pair_096fdb3dd37249ad87a28d0f28747f63","disabled":false},{"name":"Cookie","value":"session={{mySession}}","id":"pair_a93999a7a32a465e9819095263a5c343","disabled":false}],"authentication":{},"metaSortKey":-1636684177405.625,"isPrivate":false,"settingStoreCookies":true,"settingSendCookies":true,"settingDisableRenderRequestBody":false,"settingEncodeUrl":true,"settingRebuildPath":true,"settingFollowRedirects":"global","_type":"request"},{"_id":"req_356c41187c9a41fab9983a4348a3b453","parentId":"fld_5af52d0a246640b29db28d4926aa6a99","modified":1637651044519,"created":1637625649569,"url":"{{host}}/.netlify/functions/graphql","name":"Delete User","description":"","method":"POST","body":{"mimeType":"application/graphql","text":"{\"query\":\"  mutation DeleteUserMutation($id: Int!) {\\n    deleteUser(id: $id) {\\n      id\\n      name\\n    }\\n  }\",\"variables\":{\"id\":1397},\"operationName\":\"DeleteUserMutation\"}"},"parameters":[],"headers":[{"name":"Connection","value":"keep-alive","id":"pair_46b9b06c34d348a592b74406d63f303c","disabled":false},{"name":"authorization","value":"{{myBearer}}","id":"pair_dd4d347b547f4ecdaa1cec7895338184","disabled":false},{"name":"content-type","value":"application/json","id":"pair_eeecb84539f34cacae18836e5395a4d1"},{"name":"auth-provider","value":"dbAuth","id":"pair_096fdb3dd37249ad87a28d0f28747f63","disabled":false},{"name":"Cookie","value":"session={{mySession}}","id":"pair_a93999a7a32a465e9819095263a5c343","disabled":false}],"authentication":{},"metaSortKey":-1636677273812.9688,"isPrivate":false,"settingStoreCookies":true,"settingSendCookies":true,"settingDisableRenderRequestBody":false,"settingEncodeUrl":true,"settingRebuildPath":true,"settingFollowRedirects":"global","_type":"request"},{"_id":"req_32cd141d7a034ab2a24a81089d22f294","parentId":"fld_82a94f981f8d40e4ae884f41394f10d1","modified":1637651064473,"created":1637625813193,"url":"{{host}}/.netlify/functions/graphql","name":"Group Roles","description":"","method":"POST","body":{"mimeType":"application/graphql","text":"{\"query\":\" query getGroupRoles {\\n  groupRoles {\\n    id\\n    group {\\n      name\\n      id\\n    }\\n    role\\n  }\\n}\",\"operationName\":\"getGroupRoles\"}"},"parameters":[],"headers":[{"name":"Connection","value":"keep-alive","id":"pair_46b9b06c34d348a592b74406d63f303c","disabled":false},{"name":"authorization","value":"{{myBearer}}","id":"pair_dd4d347b547f4ecdaa1cec7895338184","disabled":false},{"name":"content-type","value":"application/json","id":"pair_eeecb84539f34cacae18836e5395a4d1"},{"name":"auth-provider","value":"dbAuth","id":"pair_096fdb3dd37249ad87a28d0f28747f63","disabled":false},{"name":"Cookie","value":"session={{mySession}}","id":"pair_a93999a7a32a465e9819095263a5c343","disabled":false}],"authentication":{},"metaSortKey":-1636987936082.5,"isPrivate":false,"settingStoreCookies":true,"settingSendCookies":true,"settingDisableRenderRequestBody":false,"settingEncodeUrl":true,"settingRebuildPath":true,"settingFollowRedirects":"global","_type":"request"},{"_id":"fld_82a94f981f8d40e4ae884f41394f10d1","parentId":"wrk_2df22d9915c4490eb040c83342d1f745","modified":1637625813191,"created":1637625813191,"name":"Group Roles","description":"","environment":{},"environmentPropertyOrder":null,"metaSortKey":-1637542513047,"_type":"request_group"},{"_id":"req_c763ee02225c4a4cbc8746d765873423","parentId":"fld_82a94f981f8d40e4ae884f41394f10d1","modified":1637651059177,"created":1637625813196,"url":"{{host}}/.netlify/functions/graphql","name":"Create Group Role","description":"","method":"POST","body":{"mimeType":"application/graphql","text":"{\"query\":\"  mutation CreateGroupRoleMutation(\\n    $input: CreateGroupRoleInput!\\n  ) {\\n    createGroupRole(input: $input) {\\n      id\\n      groupId\\n      role\\n    }\\n  }\",\"variables\":{\"input\":{\"groupId\":1,\"role\":\"somethingSpecial\"}},\"operationName\":\"CreateGroupRoleMutation\"}"},"parameters":[],"headers":[{"name":"Connection","value":"keep-alive","id":"pair_46b9b06c34d348a592b74406d63f303c","disabled":false},{"name":"authorization","value":"{{myBearer}}","id":"pair_dd4d347b547f4ecdaa1cec7895338184","disabled":false},{"name":"content-type","value":"application/json","id":"pair_eeecb84539f34cacae18836e5395a4d1"},{"name":"auth-provider","value":"dbAuth","id":"pair_096fdb3dd37249ad87a28d0f28747f63","disabled":false},{"name":"Cookie","value":"session={{mySession}}","id":"pair_a93999a7a32a465e9819095263a5c343","disabled":false}],"authentication":{},"metaSortKey":-1636987936132.5,"isPrivate":false,"settingStoreCookies":true,"settingSendCookies":true,"settingDisableRenderRequestBody":false,"settingEncodeUrl":true,"settingRebuildPath":true,"settingFollowRedirects":"global","_type":"request"},{"_id":"req_d5556fd580f3445f94abe068a71a4c6a","parentId":"fld_82a94f981f8d40e4ae884f41394f10d1","modified":1637651071069,"created":1637625813200,"url":"{{host}}/.netlify/functions/graphql","name":"Group Role by id","description":"","method":"POST","body":{"mimeType":"application/graphql","text":"{\"query\":\"query getGroupRoleByID($id: Int!) {\\n  group: groupRole(id: $id) {\\n    id\\n    group {\\n      name\\n    }\\n    role\\n  }\\n}\",\"variables\":{\"id\":7189},\"operationName\":\"getGroupRoleByID\"}"},"parameters":[],"headers":[{"name":"Connection","value":"keep-alive","id":"pair_46b9b06c34d348a592b74406d63f303c","disabled":false},{"name":"authorization","value":"{{myBearer}}","id":"pair_dd4d347b547f4ecdaa1cec7895338184","disabled":false},{"name":"content-type","value":"application/json","id":"pair_eeecb84539f34cacae18836e5395a4d1"},{"name":"auth-provider","value":"dbAuth","id":"pair_096fdb3dd37249ad87a28d0f28747f63","disabled":false},{"name":"Cookie","value":"session={{mySession}}","id":"pair_a93999a7a32a465e9819095263a5c343","disabled":false}],"authentication":{},"metaSortKey":-1636987936032.5,"isPrivate":false,"settingStoreCookies":true,"settingSendCookies":true,"settingDisableRenderRequestBody":false,"settingEncodeUrl":true,"settingRebuildPath":true,"settingFollowRedirects":"global","_type":"request"},{"_id":"req_f00191ffae1f406891f63afb1e89c672","parentId":"fld_82a94f981f8d40e4ae884f41394f10d1","modified":1637651082199,"created":1637625813208,"url":"{{host}}/.netlify/functions/graphql","name":"Update Group Role","description":"","method":"POST","body":{"mimeType":"application/graphql","text":"{\"query\":\"  mutation UpdateGroupRoleMutation(\\n    $id: Int!\\n    $input: UpdateGroupRoleInput!\\n  ) {\\n    updateGroupRole(id: $id, input: $input) {\\n      id\\n      group {\\n        name\\n      }\\n      role\\n    }\\n  }\",\"variables\":{\"id\":7189,\"input\":{\"role\":\"test\"}},\"operationName\":\"UpdateGroupRoleMutation\"}"},"parameters":[],"headers":[{"name":"Connection","value":"keep-alive","id":"pair_46b9b06c34d348a592b74406d63f303c","disabled":false},{"name":"authorization","value":"{{myBearer}}","id":"pair_dd4d347b547f4ecdaa1cec7895338184","disabled":false},{"name":"content-type","value":"application/json","id":"pair_eeecb84539f34cacae18836e5395a4d1"},{"name":"auth-provider","value":"dbAuth","id":"pair_096fdb3dd37249ad87a28d0f28747f63","disabled":false},{"name":"Cookie","value":"session={{mySession}}","id":"pair_a93999a7a32a465e9819095263a5c343","disabled":false}],"authentication":{},"metaSortKey":-1636987935982.5,"isPrivate":false,"settingStoreCookies":true,"settingSendCookies":true,"settingDisableRenderRequestBody":false,"settingEncodeUrl":true,"settingRebuildPath":true,"settingFollowRedirects":"global","_type":"request"},{"_id":"req_1a276462d75042329d65d5aab1767159","parentId":"fld_82a94f981f8d40e4ae884f41394f10d1","modified":1637651086812,"created":1637625813212,"url":"{{host}}/.netlify/functions/graphql","name":"Delete Group Role","description":"","method":"POST","body":{"mimeType":"application/graphql","text":"{\"query\":\"  mutation DeleteGroupRoleMutation($id: Int!) {\\n    deleteGroupRole(id: $id) {\\n      id\\n    }\\n  }\",\"variables\":{\"id\":7190},\"operationName\":\"DeleteGroupRoleMutation\"}"},"parameters":[],"headers":[{"name":"Connection","value":"keep-alive","id":"pair_46b9b06c34d348a592b74406d63f303c","disabled":false},{"name":"authorization","value":"{{myBearer}}","id":"pair_dd4d347b547f4ecdaa1cec7895338184","disabled":false},{"name":"content-type","value":"application/json","id":"pair_eeecb84539f34cacae18836e5395a4d1"},{"name":"auth-provider","value":"dbAuth","id":"pair_096fdb3dd37249ad87a28d0f28747f63","disabled":false},{"name":"Cookie","value":"session={{mySession}}","id":"pair_a93999a7a32a465e9819095263a5c343","disabled":false}],"authentication":{},"metaSortKey":-1636932707191.25,"isPrivate":false,"settingStoreCookies":true,"settingSendCookies":true,"settingDisableRenderRequestBody":false,"settingEncodeUrl":true,"settingRebuildPath":true,"settingFollowRedirects":"global","_type":"request"},{"_id":"req_274db5dd70984998bbd9f256bd7496fd","parentId":"fld_82a94f981f8d40e4ae884f41394f10d1","modified":1637651077052,"created":1637626237337,"url":"{{host}}/.netlify/functions/graphql","name":"groupRolesByGroup","description":"","method":"POST","body":{"mimeType":"application/graphql","text":"{\"query\":\"query groupRolesByGroup($id: Int!) {\\n  group: groupRolesByGroup(id: $id) {\\n    role\\n  }\\n}\",\"variables\":{\"id\":2},\"operationName\":\"groupRolesByGroup\"}"},"parameters":[],"headers":[{"name":"Connection","value":"keep-alive","id":"pair_46b9b06c34d348a592b74406d63f303c","disabled":false},{"name":"authorization","value":"{{myBearer}}","id":"pair_dd4d347b547f4ecdaa1cec7895338184","disabled":false},{"name":"content-type","value":"application/json","id":"pair_eeecb84539f34cacae18836e5395a4d1"},{"name":"auth-provider","value":"dbAuth","id":"pair_096fdb3dd37249ad87a28d0f28747f63","disabled":false},{"name":"Cookie","value":"session={{mySession}}","id":"pair_a93999a7a32a465e9819095263a5c343","disabled":false}],"authentication":{},"metaSortKey":-1636987936007.5,"isPrivate":false,"settingStoreCookies":true,"settingSendCookies":true,"settingDisableRenderRequestBody":false,"settingEncodeUrl":true,"settingRebuildPath":true,"settingFollowRedirects":"global","_type":"request"},{"_id":"req_1644bff79d094bccb2c986c23814ebe2","parentId":"fld_6d37e7cb251b4c5c9699355998a5517d","modified":1637651220700,"created":1637626829176,"url":"{{host}}/.netlify/functions/graphql","name":"Preferences","description":"","method":"POST","body":{"mimeType":"application/graphql","text":"{\"query\":\" query getPreferenes {\\n  preferences {\\n    id\\n    entity\\n    value\\n    userId\\n    user {\\n      name\\n    }\\n  }\\n}\",\"operationName\":\"getPreferenes\"}"},"parameters":[],"headers":[{"name":"Connection","value":"keep-alive","id":"pair_46b9b06c34d348a592b74406d63f303c","disabled":false},{"name":"authorization","value":"{{myBearer}}","id":"pair_dd4d347b547f4ecdaa1cec7895338184","disabled":false},{"name":"content-type","value":"application/json","id":"pair_eeecb84539f34cacae18836e5395a4d1"},{"name":"auth-provider","value":"dbAuth","id":"pair_096fdb3dd37249ad87a28d0f28747f63","disabled":false},{"name":"Cookie","value":"session={{mySession}}","id":"pair_a93999a7a32a465e9819095263a5c343","disabled":false}],"authentication":{},"metaSortKey":-1636987936082.5,"isPrivate":false,"settingStoreCookies":true,"settingSendCookies":true,"settingDisableRenderRequestBody":false,"settingEncodeUrl":true,"settingRebuildPath":true,"settingFollowRedirects":"global","_type":"request"},{"_id":"fld_6d37e7cb251b4c5c9699355998a5517d","parentId":"wrk_2df22d9915c4490eb040c83342d1f745","modified":1637626839095,"created":1637626829174,"name":"Preferences","description":"","environment":{},"environmentPropertyOrder":null,"metaSortKey":-1637540224495,"_type":"request_group"},{"_id":"req_585a9313cfcf482ea2f843b9c2c07319","parentId":"fld_6d37e7cb251b4c5c9699355998a5517d","modified":1637651131280,"created":1637626829182,"url":"{{host}}/.netlify/functions/graphql","name":"Create Preference","description":"","method":"POST","body":{"mimeType":"application/graphql","text":"{\"query\":\"  mutation CreatePreferenceMutation(\\n    $input: CreatePreferenceInput!\\n  ) {\\n    createPreference(input: $input) {\\n      id\\n      entity\\n      value\\n    }\\n  }\",\"variables\":{\"input\":{\"entity\":\"language\",\"value\":\"english\",\"userId\":1363}},\"operationName\":\"CreatePreferenceMutation\"}"},"parameters":[],"headers":[{"name":"Connection","value":"keep-alive","id":"pair_46b9b06c34d348a592b74406d63f303c","disabled":false},{"name":"authorization","value":"{{myBearer}}","id":"pair_dd4d347b547f4ecdaa1cec7895338184","disabled":false},{"name":"content-type","value":"application/json","id":"pair_eeecb84539f34cacae18836e5395a4d1"},{"name":"auth-provider","value":"dbAuth","id":"pair_096fdb3dd37249ad87a28d0f28747f63","disabled":false},{"name":"Cookie","value":"session={{mySession}}","id":"pair_a93999a7a32a465e9819095263a5c343","disabled":false}],"authentication":{},"metaSortKey":-1636987936132.5,"isPrivate":false,"settingStoreCookies":true,"settingSendCookies":true,"settingDisableRenderRequestBody":false,"settingEncodeUrl":true,"settingRebuildPath":true,"settingFollowRedirects":"global","_type":"request"},{"_id":"req_e5c697c156a641419a205c37e86b9b07","parentId":"fld_6d37e7cb251b4c5c9699355998a5517d","modified":1637651140291,"created":1637626829186,"url":"{{host}}/.netlify/functions/graphql","name":"Preference by id","description":"","method":"POST","body":{"mimeType":"application/graphql","text":"{\"query\":\"query getPreference($id: Int!) {\\n  preference(id: $id) {\\n    id\\n    entity\\n    value\\n    user {\\n      name\\n      id\\n    }\\n  }\\n}\",\"variables\":{\"id\":1},\"operationName\":\"getPreference\"}"},"parameters":[],"headers":[{"name":"Connection","value":"keep-alive","id":"pair_46b9b06c34d348a592b74406d63f303c","disabled":false},{"name":"authorization","value":"{{myBearer}}","id":"pair_dd4d347b547f4ecdaa1cec7895338184","disabled":false},{"name":"content-type","value":"application/json","id":"pair_eeecb84539f34cacae18836e5395a4d1"},{"name":"auth-provider","value":"dbAuth","id":"pair_096fdb3dd37249ad87a28d0f28747f63","disabled":false},{"name":"Cookie","value":"session={{mySession}}","id":"pair_a93999a7a32a465e9819095263a5c343","disabled":false}],"authentication":{},"metaSortKey":-1636987936032.5,"isPrivate":false,"settingStoreCookies":true,"settingSendCookies":true,"settingDisableRenderRequestBody":false,"settingEncodeUrl":true,"settingRebuildPath":true,"settingFollowRedirects":"global","_type":"request"},{"_id":"req_2a3a77ba3d1446ce98316846b350cee6","parentId":"fld_6d37e7cb251b4c5c9699355998a5517d","modified":1637651145536,"created":1637626829194,"url":"{{host}}/.netlify/functions/graphql","name":"Update Preference","description":"","method":"POST","body":{"mimeType":"application/graphql","text":"{\"query\":\"  mutation UpdatePreferenceMutation(\\n    $id: Int!\\n    $input: UpdatePreferenceInput!\\n  ) {\\n    updatePreference(id: $id, input: $input) {\\n      id\\n      entity\\n      value\\n    }\\n  }\",\"variables\":{\"id\":1,\"input\":{\"entity\":\"Worker Bees\",\"value\":\"somevalue\"}},\"operationName\":\"UpdatePreferenceMutation\"}"},"parameters":[],"headers":[{"name":"Connection","value":"keep-alive","id":"pair_46b9b06c34d348a592b74406d63f303c","disabled":false},{"name":"authorization","value":"{{myBearer}}","id":"pair_dd4d347b547f4ecdaa1cec7895338184","disabled":false},{"name":"content-type","value":"application/json","id":"pair_eeecb84539f34cacae18836e5395a4d1"},{"name":"auth-provider","value":"dbAuth","id":"pair_096fdb3dd37249ad87a28d0f28747f63","disabled":false},{"name":"Cookie","value":"session={{mySession}}","id":"pair_a93999a7a32a465e9819095263a5c343","disabled":false}],"authentication":{},"metaSortKey":-1636987935982.5,"isPrivate":false,"settingStoreCookies":true,"settingSendCookies":true,"settingDisableRenderRequestBody":false,"settingEncodeUrl":true,"settingRebuildPath":true,"settingFollowRedirects":"global","_type":"request"},{"_id":"req_f80d96c79a4e4a3a92b8b84b187c80d7","parentId":"fld_6d37e7cb251b4c5c9699355998a5517d","modified":1637651167204,"created":1637626829198,"url":"{{host}}/.netlify/functions/graphql","name":"Delete Preference","description":"","method":"POST","body":{"mimeType":"application/graphql","text":"{\"query\":\"  mutation DeletePreferenceMutation($id: Int!) {\\n    deletePreference(id: $id) {\\n      id\\n      entity\\n    }\\n  }\",\"variables\":{\"id\":1},\"operationName\":\"DeletePreferenceMutation\"}"},"parameters":[],"headers":[{"name":"Connection","value":"keep-alive","id":"pair_46b9b06c34d348a592b74406d63f303c","disabled":false},{"name":"authorization","value":"{{myBearer}}","id":"pair_dd4d347b547f4ecdaa1cec7895338184","disabled":false},{"name":"content-type","value":"application/json","id":"pair_eeecb84539f34cacae18836e5395a4d1"},{"name":"auth-provider","value":"dbAuth","id":"pair_096fdb3dd37249ad87a28d0f28747f63","disabled":false},{"name":"Cookie","value":"session={{mySession}}","id":"pair_a93999a7a32a465e9819095263a5c343","disabled":false}],"authentication":{},"metaSortKey":-1636932707191.25,"isPrivate":false,"settingStoreCookies":true,"settingSendCookies":true,"settingDisableRenderRequestBody":false,"settingEncodeUrl":true,"settingRebuildPath":true,"settingFollowRedirects":"global","_type":"request"},{"_id":"req_c0101c293a6b42c484701f6703c69a13","parentId":"fld_cf3d42cf88f14863b325eddf4a917290","modified":1637651102635,"created":1637542188216,"url":"{{host}}/.netlify/functions/graphql","name":"Load Group Member By Id","description":"","method":"POST","body":{"mimeType":"application/graphql","text":"{\"query\":\"  query GetGroupMemberById($id: Int!) {\\n    groupMember: groupMember(id: $id) {\\n      id\\n      user {\\n        name\\n        id\\n      }\\n      group {\\n        name\\n        id\\n      }\\n    }\\n  }\",\"variables\":{\"id\":1382},\"operationName\":\"GetGroupMemberById\"}"},"parameters":[],"headers":[{"name":"Connection","value":"keep-alive","id":"pair_46b9b06c34d348a592b74406d63f303c","disabled":false},{"name":"authorization","value":"{{myBearer}}","id":"pair_dd4d347b547f4ecdaa1cec7895338184","disabled":false},{"name":"content-type","value":"application/json","id":"pair_eeecb84539f34cacae18836e5395a4d1"},{"name":"auth-provider","value":"dbAuth","id":"pair_096fdb3dd37249ad87a28d0f28747f63","disabled":false},{"name":"Cookie","value":"session={{mySession}}","id":"pair_a93999a7a32a465e9819095263a5c343","disabled":false}],"authentication":{},"metaSortKey":-1637625852290,"isPrivate":false,"settingStoreCookies":true,"settingSendCookies":true,"settingDisableRenderRequestBody":false,"settingEncodeUrl":true,"settingRebuildPath":true,"settingFollowRedirects":"global","_type":"request"},{"_id":"fld_cf3d42cf88f14863b325eddf4a917290","parentId":"wrk_2df22d9915c4490eb040c83342d1f745","modified":1637626883711,"created":1637626870999,"name":"Group Members","description":"","environment":{},"environmentPropertyOrder":null,"metaSortKey":-1637541368796,"_type":"request_group"},{"_id":"req_7ca8696991d1488e8db4d99443767de3","parentId":"fld_cf3d42cf88f14863b325eddf4a917290","modified":1637651120593,"created":1637542370953,"url":"{{host}}/.netlify/functions/graphql","name":"Update Group Member","description":"","method":"POST","body":{"mimeType":"application/graphql","text":"{\"query\":\"  mutation UpdateGroupMemberMutation(\\n    $id: Int!\\n    $input: UpdateGroupMemberInput!\\n  ) {\\n    updateGroupMember(id: $id, input: $input) {\\n      id\\n      user {\\n        name\\n        id\\n      }\\n      group {\\n        name\\n        id\\n      }\\n    }\\n  }\",\"variables\":{\"id\":1382,\"input\":{\"groupId\":2}},\"operationName\":\"UpdateGroupMemberMutation\"}"},"parameters":[],"headers":[{"name":"Connection","value":"keep-alive","id":"pair_46b9b06c34d348a592b74406d63f303c","disabled":false},{"name":"authorization","value":"{{myBearer}}","id":"pair_dd4d347b547f4ecdaa1cec7895338184","disabled":false},{"name":"content-type","value":"application/json","id":"pair_eeecb84539f34cacae18836e5395a4d1"},{"name":"auth-provider","value":"dbAuth","id":"pair_096fdb3dd37249ad87a28d0f28747f63","disabled":false},{"name":"Cookie","value":"session={{mySession}}","id":"pair_a93999a7a32a465e9819095263a5c343","disabled":false}],"authentication":{},"metaSortKey":-1637625852140,"isPrivate":false,"settingStoreCookies":true,"settingSendCookies":true,"settingDisableRenderRequestBody":false,"settingEncodeUrl":true,"settingRebuildPath":true,"settingFollowRedirects":"global","_type":"request"},{"_id":"req_54aa388f1bd0465abb34c79cd2e07fa9","parentId":"fld_cf3d42cf88f14863b325eddf4a917290","modified":1637651216420,"created":1637626345893,"url":"{{host}}/.netlify/functions/graphql","name":"Group Members","description":"","method":"POST","body":{"mimeType":"application/graphql","text":"{\"query\":\" query getGroupMembers {\\n  groupMembers {\\n    id\\n    group {\\n      name\\n      id\\n    }\\n    user {\\n      name\\n      id\\n    }\\n  }\\n}\",\"operationName\":\"getGroupMembers\"}"},"parameters":[],"headers":[{"name":"Connection","value":"keep-alive","id":"pair_46b9b06c34d348a592b74406d63f303c","disabled":false},{"name":"authorization","value":"{{myBearer}}","id":"pair_dd4d347b547f4ecdaa1cec7895338184","disabled":false},{"name":"content-type","value":"application/json","id":"pair_eeecb84539f34cacae18836e5395a4d1"},{"name":"auth-provider","value":"dbAuth","id":"pair_096fdb3dd37249ad87a28d0f28747f63","disabled":false},{"name":"Cookie","value":"session={{mySession}}","id":"pair_a93999a7a32a465e9819095263a5c343","disabled":false}],"authentication":{},"metaSortKey":-1637625852340,"isPrivate":false,"settingStoreCookies":true,"settingSendCookies":true,"settingDisableRenderRequestBody":false,"settingEncodeUrl":true,"settingRebuildPath":true,"settingFollowRedirects":"global","_type":"request"},{"_id":"req_bf5c6493a1af48a8a0a6820580ccc44e","parentId":"fld_cf3d42cf88f14863b325eddf4a917290","modified":1637651092605,"created":1637626345904,"url":"{{host}}/.netlify/functions/graphql","name":"Create Group Member","description":"","method":"POST","body":{"mimeType":"application/graphql","text":"{\"query\":\"  mutation CreateGroupMemberMutation(\\n    $input: CreateGroupMemberInput!\\n  ) {\\n    createGroupMember(input: $input) {\\n      id\\n      groupId\\n      userId\\n    }\\n  }\",\"variables\":{\"input\":{\"groupId\":1,\"userId\":1395}},\"operationName\":\"CreateGroupMemberMutation\"}"},"parameters":[],"headers":[{"name":"Connection","value":"keep-alive","id":"pair_46b9b06c34d348a592b74406d63f303c","disabled":false},{"name":"authorization","value":"{{myBearer}}","id":"pair_dd4d347b547f4ecdaa1cec7895338184","disabled":false},{"name":"content-type","value":"application/json","id":"pair_eeecb84539f34cacae18836e5395a4d1"},{"name":"auth-provider","value":"dbAuth","id":"pair_096fdb3dd37249ad87a28d0f28747f63","disabled":false},{"name":"Cookie","value":"session={{mySession}}","id":"pair_a93999a7a32a465e9819095263a5c343","disabled":false}],"authentication":{},"metaSortKey":-1637625852390,"isPrivate":false,"settingStoreCookies":true,"settingSendCookies":true,"settingDisableRenderRequestBody":false,"settingEncodeUrl":true,"settingRebuildPath":true,"settingFollowRedirects":"global","_type":"request"},{"_id":"req_cbf3574fbed84da5a2246c53ce59f7be","parentId":"fld_cf3d42cf88f14863b325eddf4a917290","modified":1637651125472,"created":1637626345921,"url":"{{host}}/.netlify/functions/graphql","name":"Delete Group Role","description":"","method":"POST","body":{"mimeType":"application/graphql","text":"{\"query\":\"  mutation DeleteGroupMemberMutation($id: Int!) {\\n    deleteGroupMember(id: $id) {\\n      id\\n    }\\n  }\",\"variables\":{\"id\":1382},\"operationName\":\"DeleteGroupMemberMutation\"}"},"parameters":[],"headers":[{"name":"Connection","value":"keep-alive","id":"pair_46b9b06c34d348a592b74406d63f303c","disabled":false},{"name":"authorization","value":"{{myBearer}}","id":"pair_dd4d347b547f4ecdaa1cec7895338184","disabled":false},{"name":"content-type","value":"application/json","id":"pair_eeecb84539f34cacae18836e5395a4d1"},{"name":"auth-provider","value":"dbAuth","id":"pair_096fdb3dd37249ad87a28d0f28747f63","disabled":false},{"name":"Cookie","value":"session={{mySession}}","id":"pair_a93999a7a32a465e9819095263a5c343","disabled":false}],"authentication":{},"metaSortKey":-1637625852090,"isPrivate":false,"settingStoreCookies":true,"settingSendCookies":true,"settingDisableRenderRequestBody":false,"settingEncodeUrl":true,"settingRebuildPath":true,"settingFollowRedirects":"global","_type":"request"},{"_id":"req_fc16c6b833ed4995be672052b5a3c0df","parentId":"fld_cf3d42cf88f14863b325eddf4a917290","modified":1637651107084,"created":1637626345932,"url":"{{host}}/.netlify/functions/graphql","name":"groupMembersByGroup","description":"","method":"POST","body":{"mimeType":"application/graphql","text":"{\"query\":\"query groupMembersByGroup($id: Int!) {\\n  group: groupMembersByGroup(id: $id) {\\n    user {\\n      name\\n      id\\n    }\\n  }\\n}\",\"variables\":{\"id\":1},\"operationName\":\"groupMembersByGroup\"}"},"parameters":[],"headers":[{"name":"Connection","value":"keep-alive","id":"pair_46b9b06c34d348a592b74406d63f303c","disabled":false},{"name":"authorization","value":"{{myBearer}}","id":"pair_dd4d347b547f4ecdaa1cec7895338184","disabled":false},{"name":"content-type","value":"application/json","id":"pair_eeecb84539f34cacae18836e5395a4d1"},{"name":"auth-provider","value":"dbAuth","id":"pair_096fdb3dd37249ad87a28d0f28747f63","disabled":false},{"name":"Cookie","value":"session={{mySession}}","id":"pair_a93999a7a32a465e9819095263a5c343","disabled":false}],"authentication":{},"metaSortKey":-1637625852240,"isPrivate":false,"settingStoreCookies":true,"settingSendCookies":true,"settingDisableRenderRequestBody":false,"settingEncodeUrl":true,"settingRebuildPath":true,"settingFollowRedirects":"global","_type":"request"},{"_id":"req_2b6f63f682d54098be73918306fa9c5d","parentId":"fld_cf3d42cf88f14863b325eddf4a917290","modified":1637651115917,"created":1637626383696,"url":"{{host}}/.netlify/functions/graphql","name":"groupMembersByUser","description":"","method":"POST","body":{"mimeType":"application/graphql","text":"{\"query\":\"query groupMembersByUser($id: Int!) {\\n  group: groupMembersByUser(id: $id) {\\n    id\\n    group {\\n      name\\n      id\\n    }\\n  }\\n}\",\"variables\":{\"id\":1343},\"operationName\":\"groupMembersByUser\"}"},"parameters":[],"headers":[{"name":"Connection","value":"keep-alive","id":"pair_46b9b06c34d348a592b74406d63f303c","disabled":false},{"name":"authorization","value":"{{myBearer}}","id":"pair_dd4d347b547f4ecdaa1cec7895338184","disabled":false},{"name":"content-type","value":"application/json","id":"pair_eeecb84539f34cacae18836e5395a4d1"},{"name":"auth-provider","value":"dbAuth","id":"pair_096fdb3dd37249ad87a28d0f28747f63","disabled":false},{"name":"Cookie","value":"session={{mySession}}","id":"pair_a93999a7a32a465e9819095263a5c343","disabled":false}],"authentication":{},"metaSortKey":-1637625852190,"isPrivate":false,"settingStoreCookies":true,"settingSendCookies":true,"settingDisableRenderRequestBody":false,"settingEncodeUrl":true,"settingRebuildPath":true,"settingFollowRedirects":"global","_type":"request"},{"_id":"env_6b24235a2e7192cf8b578035363b20fc70ae9814","parentId":"wrk_2df22d9915c4490eb040c83342d1f745","modified":1637651166260,"created":1637540192214,"name":"Base Environment","data":{"myBearer":"Bearer (userid)","mySession":"secret","host":"https://demo.tskr.io"},"dataPropertyOrder":{"&":["myBearer","mySession","host"]},"color":null,"isPrivate":false,"metaSortKey":1637540192215,"_type":"environment"},{"_id":"jar_6b24235a2e7192cf8b578035363b20fc70ae9814","parentId":"wrk_2df22d9915c4490eb040c83342d1f745","modified":1637540192217,"created":1637540192217,"name":"Default Jar","cookies":[],"_type":"cookie_jar"},{"_id":"spc_baaedb6a5cb548cdb2d9f553db5a5f2b","parentId":"wrk_2df22d9915c4490eb040c83342d1f745","modified":1637540192211,"created":1637540192211,"fileName":"Tskr","contents":"","contentType":"yaml","_type":"api_spec"}]}